CHANGELOG
MANIFEST.in
README.rst
setup.py
bin/run_pyfeat.py
examples/README.md
examples/double_well_example.ipynb
examples/trajectory_factory.py
pyfeat/__init__.py
pyfeat.egg-info/PKG-INFO
pyfeat.egg-info/SOURCES.txt
pyfeat.egg-info/dependency_links.txt
pyfeat.egg-info/requires.txt
pyfeat.egg-info/top_level.txt
pyfeat/api/__init__.py
pyfeat/api/api.py
pyfeat/estimator/__init__.py
pyfeat/estimator/dtram.py
pyfeat/estimator/mbar.py
pyfeat/estimator/tram.py
pyfeat/estimator/wham.py
pyfeat/estimator/xtram.py
pyfeat/forge/__init__.py
pyfeat/forge/forge.py
pyfeat/reader/__init__.py
pyfeat/reader/reader.py
test/test_api.py
test/test_dtram.py
test/test_forge.py
test/test_mbar.py
test/test_reader.py
test/test_tram.py
test/test_wham.py
test/test_xtram.py