Metadata-Version: 1.1
Name: pyfeat
Version: 0.3.0
Summary: The python free energy analysis toolkit
Home-page: http://github.com/markovmodel/pyfeat
Author: The pyfeat team
Author-email: pyfeat@lists.fu-berlin.de
License: Simplified BSD License
Keywords: TRAM,WHAM,free energy
Platform: UNKNOWN
Classifier: Development Status :: 3 - Alpha
Classifier: Environment :: Console
Classifier: Intended Audience :: Science/Research
Classifier: License :: OSI Approved :: BSD License
Classifier: Natural Language :: English
Classifier: Operating System :: MacOS :: MacOS X
Classifier: Operating System :: POSIX :: Linux
Classifier: Programming Language :: C
Classifier: Programming Language :: Cython
Classifier: Programming Language :: Python :: 2.7
Classifier: Topic :: Scientific/Engineering :: Bio-Informatics
Classifier: Topic :: Scientific/Engineering :: Chemistry
Classifier: Topic :: Scientific/Engineering :: Mathematics
Classifier: Topic :: Scientific/Engineering :: Physics
